videocdn_tv/__init__.py
videocdn_tv/exception.py
videocdn_tv/link.py
videocdn_tv/main.py
videocdn_tv/models/__init__.py
videocdn_tv/models/api/__init__.py
videocdn_tv/models/api/anime.py
videocdn_tv/models/api/anime_tv_series.py
videocdn_tv/models/api/base_api.py
videocdn_tv/models/api/movie.py
videocdn_tv/models/api/show_tv_series.py
videocdn_tv/models/api/translations.py
videocdn_tv/models/api/tv_series.py
videocdn_tv/models/base.py
videocdn_tv/models/contents/__init__.py
videocdn_tv/models/contents/episode.py
videocdn_tv/models/contents/media.py
videocdn_tv/models/contents/qualitie.py
videocdn_tv/models/contents/translation.py
videocdn_tv/models/episodes.py
videocdn_tv/models/response.py
videocdn_tv/models/seasons.py
videocdn_tv/params/__init__.py
videocdn_tv/params/base.py
videocdn_tv/params/content.py
videocdn_tv/params/episode.py
videocdn_tv/params/season.py
videocdn_tv/request.py
videocdn_tv/type/__init__.py
videocdn_tv/type/direction.py
videocdn_tv/type/field.py
videocdn_tv/type/ordering.py
videocdn_tv-0.2.1.dist-info/METADATA
videocdn_tv-0.2.1.dist-info/WHEEL
videocdn_tv-0.2.1.dist-info/RECORD
