Metadata-Version: 2.1
Name: videocdn-tv
Version: 0.2.1
Summary: Реализация Api для сервиса VideoCDN.tv
Home-page: https://github.com/odi1n/VideoCDN
License: MIT
Keywords: videocdn,videocdn-tv
Author: Your Name
Author-email: you@example.com
Requires-Python: >=3.9,<4.0
Classifier: License :: OSI Approved :: MIT License
Classifier: Programming Language :: Python :: 3
Classifier: Programming Language :: Python :: 3.9
Classifier: Programming Language :: Python :: 3.10
Classifier: Programming Language :: Python :: 3.11
Requires-Dist: httpx (>=0.23.3,<0.24.0)
Requires-Dist: pydantic (>=1.9.2,<2.0.0)
Project-URL: Documentation, https://github.com/odi1n/VideoCDN/blob/master/README.md
Project-URL: Repository, https://github.com/odi1n/VideoCDN
